bdapt/__init__.py
bdapt/apt_operations.py
bdapt/bundle_manager.py
bdapt/cli.py
bdapt/metapackage.py
bdapt/models.py
bdapt/storage.py
bdapt/validators.py
bdapt-0.1.0.dist-info/METADATA
bdapt-0.1.0.dist-info/WHEEL
bdapt-0.1.0.dist-info/entry_points.txt
bdapt-0.1.0.dist-info/RECORD
