Metadata-Version: 2.4
Name: bdapt
Version: 0.1.0
Summary: Bundle APT - Manage groups of APT packages as dependencies
Project-URL: Homepage, https://github.com/deltazefiro/bdapt
Project-URL: Repository, https://github.com/deltazefiro/bdapt
Project-URL: Issues, https://github.com/deltazefiro/bdapt/issues
Project-URL: Changelog, https://github.com/deltazefiro/bdapt/releases
Author-email: deltazefiro <deltazefiro@gmail.com>
License: GPL-3.0-or-later
Keywords: apt,bundle,debian,dependencies,metapackage,package-manager,ubuntu
Classifier: Development Status :: 2 - Pre-Alpha
Classifier: Environment :: Console
Classifier: Intended Audience :: Developers
Classifier: Intended Audience :: System Administrators
Classifier: License :: OSI Approved :: GNU General Public License v3 or later (GPLv3+)
Classifier: Operating System :: POSIX :: Linux
Classifier: Programming Language :: Python :: 3
Classifier: Programming Language :: Python :: 3.8
Classifier: Programming Language :: Python :: 3.9
Classifier: Programming Language :: Python :: 3.10
Classifier: Programming Language :: Python :: 3.11
Classifier: Programming Language :: Python :: 3.12
Classifier: Topic :: System :: Installation/Setup
Classifier: Topic :: System :: Systems Administration
Classifier: Topic :: Utilities
Requires-Python: >=3.8
Requires-Dist: pydantic
Requires-Dist: rich
Requires-Dist: typer
Provides-Extra: dev
Requires-Dist: black; extra == 'dev'
Requires-Dist: isort; extra == 'dev'
Requires-Dist: mypy; extra == 'dev'
Requires-Dist: pytest; extra == 'dev'
Requires-Dist: pytest-cov; extra == 'dev'
